tanzania/__init__.py
tanzania/nida.py
tanzania/tanesco.py
tanzania-0.0.4.dist-info/METADATA
tanzania-0.0.4.dist-info/WHEEL
tanzania-0.0.4.dist-info/top_level.txt
tanzania-0.0.4.dist-info/RECORD
