Metadata-Version: 2.1
Name: tanzania
Version: 0.0.4
Summary: UNKNOWN
Home-page: https://github.com/kalokola/tzsinfo
Author: Brightius Kalokola
Author-email: brightiuskalokola@gmail.com
License: MIT
Platform: UNKNOWN
Classifier: Programming Language :: Python :: 3
Classifier: License :: OSI Approved :: MIT License
Classifier: Operating System :: OS Independent
Requires-Dist: requests
